{
  "series": "docker-containers",
  "total_fixes": 1,
  "issues": [
    {
      "original": "正常运行的容器近乎‘隐形’，而出现问题的容器则迅速变成‘黑盒’。容器化的隔离性是其核心价值，但也增加了调试难度。你无法直接通过 [代码] 登录容器，也无法从宿主机直接浏览其文件系统。",
      "fixed": "正常运行的容器近乎‘隐形’，而出现问题的容器则迅速变成‘黑盒’；容器化的隔离性是其核心价值，但也增加了调试难度——你无法直接通过 [代码] 登录容器或从宿主机直接浏览其文件系统。",
      "reason": "短句合并/去冗余",
      "file": "06-debugging-and-logging.md"
    },
    {
      "original": "日志是排查问题的第一道防线，Docker 会捕获容器向 stdout 和 stderr 输出的所有内容。",
      "fixed": "日志是排查问题的第一道防线，Docker 会捕获容器向 stdout 和 stderr 输出的所有内容。",
      "reason": "段落已自然",
      "file": "06-debugging-and-logging.md"
    },
    {
      "original": "这一点至关重要 —— 当容器崩溃后停止运行，其日志仍会被保留，直到该容器被显式删除（[代码]）：",
      "fixed": "这一点至关重要——当容器崩溃后停止运行，其日志仍会被保留，直到该容器被显式删除（[代码]）：",
      "reason": "去冗余",
      "file": "06-debugging-and-logging.md"
    },
    {
      "original": "退出码 137 尤其值得关注，通常意味着容器因超出内存限制而被内核 OOM killer 终止。",
      "fixed": "退出码 137 尤其值得关注，通常意味着容器因超出内存限制而被内核 OOM killer 终止。",
      "reason": "段落已自然",
      "file": "06-debugging-and-logging.md"
    },
    {
      "original": "[代码] 可在运行中的容器内执行命令，是交互式调试的主要方式：\n进入容器后，你可以进行如下排查：",
      "fixed": "[代码] 可在运行中的容器内执行命令，是交互式调试的主要方式——进入容器后，你可以进行如下排查：",
      "reason": "短句合并",
      "file": "06-debugging-and-logging.md"
    },
    {
      "original": "精简镜像（如 Alpine、 distroless）可能不包含 bash 或常用调试工具：\n对于 distroless 镜像，你根本无法 [代码] 进入（无 shell）。此时应改用调试 sidecar：",
      "fixed": "精简镜像（如 Alpine、distroless）可能不包含 bash 或常用调试工具，对于 distroless 镃像，你根本无法 [代码] 进入（无 shell），此时应改用调试 sidecar：",
      "reason": "短句合并",
      "file": "06-debugging-and-logging.md"
    },
    {
      "original": "[代码] 返回关于容器的详细 JSON 元数据。虽然输出冗长，但它包含了你能想到的一切信息：",
      "fixed": "[代码] 返回关于容器的详细 JSON 元数据，虽然输出冗长，但它包含了你能想到的一切信息：",
      "reason": "短句合并",
      "file": "06-debugging-and-logging.md"
    },
    {
      "original": "若不启用日志轮转，[代码] 日志会无限增长，最终耗尽磁盘空间：",
      "fixed": "若不启用日志轮转，[代码] 日志会无限增长，最终耗尽磁盘空间：",
      "reason": "段落已自然",
      "file": "06-debugging-and-logging.md"
    },
    {
      "original": "本系列此前的内容均围绕**单机版 Docker**展开，即仅在一台机器上运行容器。这种方式非常适合开发、小型项目及流量适中的应用，但当需要在服务器宕机时保持可用、应对突发流量高峰或实现零停机部署更新时，其局限性便立即显现。而**容器编排（Container Orchestration）**正是为解决这些问题而生——其中，Kubernetes 已成为事实上的行业标准。需要在服务器宕机时保持可用、应对突发流量高峰或实现零停机部署更新时，单机版 Docker 的局限性便立即显现。而**容器编排（Container Orchestration）**正是为解决这些问题而生——其中， Kubernetes 已成为事实上的行业标准。",
      "fixed": "本系列此前的内容均围绕**单机版 Docker**展开，即仅在一台机器上运行容器，这种方式非常适合开发、小型项目及流量适中的应用。然而，当需要在服务器宕机时保持可用、应对突发流量高峰或实现零停机部署更新时，单机版 Docker 的局限性便立即显现。而**容器编排（Container Orchestration）**正是为解决这些问题而生，其中，Kubernetes 已成为事实上的行业标准。",
      "reason": "短句合并/去冗余",
      "file": "08-orchestration-preview.md"
    }
  ]
}